<?xml version="1.0" encoding="utf-8" ?>
<dwsync>
<file name="blueButton.png" local="128476521060000000" remote="128476521060000000" testing="0" />
<file name="iui.css" local="128499430720000000" remote="128499430720000000" testing="0" />
<file name="grayButton.png" local="128476521090000000" remote="128476521090000000" testing="0" />
<file name="whiteButton.png" local="128476047660000000" remote="128476047660000000" testing="0" />
<file name="toggleOn.png" local="128476047630000000" remote="128476047630000000" testing="0" />
<file name="iuix.css" local="128476521130000000" remote="128476521130000000" testing="0" />
<file name="listArrow.png" local="128476047540000000" remote="128476047540000000" testing="0" />
<file name="iui.js" local="128487377240000000" remote="128487377240000000" testing="0" />
<file name="iuix.js" local="128476521140000000" remote="128476521140000000" testing="0" />
<file name="loading.gif" local="128476047580000000" remote="128476047580000000" testing="0" />
<file name="backButton.png" local="128476521050000000" remote="128476521050000000" testing="0" />
<file name="pinstripes.png" local="128476047590000000" remote="128476047590000000" testing="0" />
<file name="toolButton.png" local="128476047650000000" remote="128476047650000000" testing="0" />
<file name="listArrowSel.png" local="128476047550000000" remote="128476047550000000" testing="0" />
<file name="iu-baki.js" local="128487375720000000" remote="128487375720000000" testing="0" />
<file name="selection.png" local="128476047600000000" remote="128476047600000000" testing="0" />
<file name="toolbar.png" local="128476047640000000" remote="128476047640000000" testing="0" />
<file name="thumb.png" local="128476047610000000" remote="128476047610000000" testing="0" />
<file name="cancel.png" local="128476521080000000" remote="128476521080000000" testing="0" />
<file name="listGroup.png" local="128476047570000000" remote="128476047570000000" testing="0" />
<file name="toggle.png" local="128476047620000000" remote="128476047620000000" testing="0" />
</dwsync>